bulkexec/__init__.py
bulkexec/__main__.py
bulkexec-0.0.1.dist-info/METADATA
bulkexec-0.0.1.dist-info/WHEEL
bulkexec-0.0.1.dist-info/licenses/LICENSE
bulkexec-0.0.1.dist-info/RECORD
