Metadata-Version: 2.4
Name: bulkexec
Version: 0.0.1
Summary: A simple bulk shell command execution package
Project-URL: Homepage, https://github.com/tristangaudreault/bulkexec
Project-URL: Issues, https://github.com/tristangaudreault/bulkexec/issues
Author-email: Tristan Gaudreault <tristan@tristangaudreault.com>
License-Expression: MIT
License-File: LICENSE
Classifier: Operating System :: OS Independent
Classifier: Programming Language :: Python :: 3
Requires-Python: >=3.8
